[
  {
    "contractName": "SampleDto",
    "providerName": "example1",
    "version": "v1",
    "schema": {
      "type": "object",
      "id": "urn:jsonschema:com:monadiccloud:bindingz:contract:plugin:example:sbt:SampleDto",
      "properties": {
        "one": {
          "type": "string"
        }
      }
    }
  },
  {
    "contractName": "SampleDto",
    "providerName": "example2",
    "version": "v2",
    "schema": {
      "type": "object",
      "id": "urn:jsonschema:com:monadiccloud:bindingz:contract:plugin:example:sbt:SampleDto",
      "properties": {
        "one": {
          "type": "string"
        }
      }
    }
  },
  {
    "contractName": "SampleDto",
    "providerName": "example1",
    "version": "v2",
    "schema": {
      "type": "object",
      "id": "urn:jsonschema:com:monadiccloud:bindingz:contract:plugin:example:sbt:SampleDto",
      "properties": {
        "one": {
          "type": "string"
        }
      }
    }
  }
]
